{"mc":{
	"straight":{
		"frameRate":12,
		"events":[
			
			],
		"frames":[
			
			{
			"res":"2B91C75A",
			"x":91,
			"y":-60
			},
			{
			"res":"65A940E6",
			"x":61,
			"y":-43
			},
			{
			"res":"FB55B813",
			"x":31,
			"y":-27
			},
			{
			"res":"A8500929",
			"x":1,
			"y":-14
			},
			{
			"res":"A0BCA7C1",
			"x":-24,
			"y":-7
			},
			{
			"res":"26DB8F8E",
			"x":-50,
			"y":-8
			},
			{
			"res":"344A6FF6",
			"x":-74,
			"y":-18
			},
			{
			"res":"9256ED12",
			"x":-70,
			"y":-37
			},
			{
			"res":"C5A8DC49",
			"x":-68,
			"y":-51
			},
			{
			"res":"32C83C5C",
			"x":-66,
			"y":-54
			},
			{
			"res":"80F3E618",
			"x":-54,
			"y":-50
			},
			{
			"res":"C892540B",
			"x":-38,
			"y":-45
			},
			{
			"res":"467AD668",
			"x":-34,
			"y":-15
			},
			{
			"res":"60B23388",
			"x":-75,
			"y":-3
			}
			]
}},
	"res":{
		"344A6FF6":{"x":6,"y":6,"w":51,"h":42},
		"60B23388":{"x":6,"y":226,"w":27,"h":19},
		"C5A8DC49":{"x":200,"y":6,"w":32,"h":56},
		"2B91C75A":{"x":135,"y":6,"w":53,"h":36},
		"80F3E618":{"x":74,"y":181,"w":50,"h":28},
		"32C83C5C":{"x":6,"y":60,"w":48,"h":44},
		"C892540B":{"x":139,"y":54,"w":40,"h":31},
		"9256ED12":{"x":6,"y":116,"w":34,"h":54},
		"65A940E6":{"x":6,"y":182,"w":56,"h":32},
		"A8500929":{"x":69,"y":54,"w":58,"h":30},
		"26DB8F8E":{"x":69,"y":6,"w":54,"h":36},
		"FB55B813":{"x":52,"y":139,"w":57,"h":30},
		"A0BCA7C1":{"x":66,"y":96,"w":56,"h":31},
		"467AD668":{"x":134,"y":97,"w":25,"h":33}
	}}